motif_scraper/__init__.py
motif_scraper/__main__.py
motif_scraper-1.0.2.dist-info/METADATA
motif_scraper-1.0.2.dist-info/RECORD
motif_scraper-1.0.2.dist-info/WHEEL
motif_scraper-1.0.2.dist-info/entry_points.txt
motif_scraper-1.0.2.dist-info/top_level.txt
