Metadata-Version: 2.1
Name: motif-scraper
Version: 1.0.2
Summary: Tool for finding degenerate motifs in FASTA files
Home-page: https://github.com/RobersonLab/motif_scraper
Author: Elisha Roberson
Author-email: dr.eli.roberson@gmail.com
License: MIT
Keywords: degenerate sequence motif site search
Platform: UNKNOWN
Classifier: Development Status :: 5 - Production/Stable
Classifier: Environment :: Console
Classifier: Intended Audience :: Science/Research
Classifier: License :: OSI Approved :: MIT License
Classifier: Topic :: Scientific/Engineering :: Bio-Informatics
Classifier: Programming Language :: Python :: 2.7
Classifier: Programming Language :: Python :: 3
Classifier: Programming Language :: Python :: 3.2
Classifier: Programming Language :: Python :: 3.3
Classifier: Programming Language :: Python :: 3.4
Classifier: Programming Language :: Python :: 3.5
Requires-Dist: pyfaidx
Requires-Dist: regex (>=2016.01.10)
Requires-Dist: six
